xova/__init__.py
xova/testing_data.py
xova/apps/__init__.py
xova/apps/xova/__init__.py
xova/apps/xova/app.py
xova/apps/xova/arguments.py
xova/apps/xova/averaging.py
xova/apps/xova/chunking.py
xova/apps/xova/logger_init.py
xova/apps/xova/subtables.py
xova/apps/xova/utils.py
xova/apps/xova/tests/__init__.py
xova/apps/xova/tests/test_application.py
xova/apps/xova/tests/test_argparsing.py
xova/tests/__init__.py
xova-0.1.1.dist-info/AUTHORS.rst
xova-0.1.1.dist-info/LICENSE
xova-0.1.1.dist-info/METADATA
xova-0.1.1.dist-info/WHEEL
xova-0.1.1.dist-info/entry_points.txt
xova-0.1.1.dist-info/top_level.txt
xova-0.1.1.dist-info/RECORD
